CHANGES.txt
buildout.cfg
setup.py
bootstrap/bootstrap.py
src/falkolab/__init__.py
src/falkolab.extjslayer.egg-info/PKG-INFO
src/falkolab.extjslayer.egg-info/SOURCES.txt
src/falkolab.extjslayer.egg-info/dependency_links.txt
src/falkolab.extjslayer.egg-info/namespace_packages.txt
src/falkolab.extjslayer.egg-info/not-zip-safe
src/falkolab.extjslayer.egg-info/requires.txt
src/falkolab.extjslayer.egg-info/top_level.txt
src/falkolab/extjslayer/README.txt
src/falkolab/extjslayer/__init__.py
src/falkolab/extjslayer/configure.zcml
src/falkolab/extjslayer/ftesting.zcml
src/falkolab/extjslayer/interfaces.py
src/falkolab/extjslayer/sample.txt
src/falkolab/extjslayer/tests.py
src/falkolab/extjslayer/ext/CHANGES.html
src/falkolab/extjslayer/ext/INCLUDE_ORDER.txt
src/falkolab/extjslayer/ext/ext-all-debug.js
src/falkolab/extjslayer/ext/ext-all.js
src/falkolab/extjslayer/ext/ext-core-debug.js
src/falkolab/extjslayer/ext/ext-core.js
src/falkolab/extjslayer/ext/license.txt
src/falkolab/extjslayer/ext/adapter/ext/ext-base.js
src/falkolab/extjslayer/ext/adapter/jquery/ext-jquery-adapter.js
src/falkolab/extjslayer/ext/adapter/jquery/jquery.js
src/falkolab/extjslayer/ext/adapter/prototype/effects.js
src/falkolab/extjslayer/ext/adapter/prototype/ext-prototype-adapter.js
src/falkolab/extjslayer/ext/adapter/prototype/prototype.js
src/falkolab/extjslayer/ext/adapter/prototype/scriptaculous.js
src/falkolab/extjslayer/ext/adapter/yui/ext-yui-adapter.js
src/falkolab/extjslayer/ext/adapter/yui/yui-utilities.js
src/falkolab/extjslayer/ext/air/README.txt
src/falkolab/extjslayer/ext/air/air.jsb
src/falkolab/extjslayer/ext/air/ext-air.js
src/falkolab/extjslayer/ext/air/resources/air-resources.jsb
src/falkolab/extjslayer/ext/air/resources/ext-air.css
src/falkolab/extjslayer/ext/air/resources/icons/extlogo128.png
src/falkolab/extjslayer/ext/air/resources/icons/extlogo16.png
src/falkolab/extjslayer/ext/air/resources/icons/extlogo32.png
src/falkolab/extjslayer/ext/air/resources/icons/extlogo48.png
src/falkolab/extjslayer/ext/air/resources/icons/extlogo64.png
src/falkolab/extjslayer/ext/air/resources/images/left-corners.png
src/falkolab/extjslayer/ext/air/resources/images/left-right.png
src/falkolab/extjslayer/ext/air/resources/images/right-corners.png
src/falkolab/extjslayer/ext/air/resources/images/top-bottom.png
